pydahua/__init__.py
pydahua/biometric.py
pydahua-0.1.1.dist-info/licenses/LICENSE
pydahua-0.1.1.dist-info/METADATA
pydahua-0.1.1.dist-info/WHEEL
pydahua-0.1.1.dist-info/top_level.txt
pydahua-0.1.1.dist-info/RECORD
