Metadata-Version: 2.4
Name: pydahua
Version: 0.1.1
Summary: Dahua biometric Python integration library
Home-page: https://github.com/KSreethul/pydahua
Author: Sreethul Krishna
Author-email: Sreethul Krishna <sreethulkrishna24@gmail.com>
License: LGPL 3.0
Project-URL: Homepage, https://github.com/KSreethul/pydahua
Project-URL: Bug Tracker, https://github.com/KSreethul/pydahua/issues
Keywords: biometric,dahua,attendance,device,integration,Time Attendance - Dahua,python,API,Dahua API,biometric Python,attendance system,face recognition,Access Control
Requires-Python: >=3.10
License-File: LICENSE
Requires-Dist: requests>=2.0
Dynamic: author
Dynamic: home-page
Dynamic: license-file
Dynamic: requires-python
